station/plugin/plugin2/__init__.py
station/plugin/plugin2/constants.py
station/plugin/plugin2/plugin.py
station_plugin2-1.0.1.dist-info/METADATA
station_plugin2-1.0.1.dist-info/WHEEL
station_plugin2-1.0.1.dist-info/top_level.txt
station_plugin2-1.0.1.dist-info/RECORD
