Metadata-Version: 2.1
Name: station-plugin2
Version: 1.0.1
Summary: Station plugin : plugin 2
License: Station Corp Software License Agreement
